simplegoogleapi/__init__.py
simplegoogleapi/auth/__init__.py
simplegoogleapi/auth/main.py
simplegoogleapi/drive/__init__.py
simplegoogleapi/drive/help.py
simplegoogleapi/drive/main.py
simplegoogleapi-0.1.1.dist-info/LICENSE
simplegoogleapi-0.1.1.dist-info/METADATA
simplegoogleapi-0.1.1.dist-info/WHEEL
simplegoogleapi-0.1.1.dist-info/top_level.txt
simplegoogleapi-0.1.1.dist-info/RECORD
