Metadata-Version: 2.1
Name: simplegoogleapi
Version: 0.1.1
Summary: A simple way to work with Google API
Home-page: https://github.com/tranngocminhhieu/simple-google-api
Author: Tran Ngoc Minh Hieu
Author-email: tnmhieu@gmail.com
License-File: LICENSE
Requires-Dist: requests
Requires-Dist: pydrive2
Requires-Dist: google-api-python-client
Requires-Dist: oauth2client
